setup.py
src/colourless/__init__.py
src/colourless/script.py
src/colourless.egg-info/PKG-INFO
src/colourless.egg-info/SOURCES.txt
src/colourless.egg-info/dependency_links.txt
src/colourless.egg-info/entry_points.txt
src/colourless.egg-info/requires.txt
src/colourless.egg-info/top_level.txt