Metadata-Version: 1.0
Name: colourless
Version: 0.0.1
Summary: Create a colour.less file from a colourlovers palette
Home-page: UNKNOWN
Author: Jake Hickenlooper
Author-email: jake@weboftomorrow.com
License: UNKNOWN
Platform: UNKNOWN
